MANIFEST.in
Pipfile
Pipfile.lock
README.md
setup.py
generic_report_generator_psql/PSQLDropTempTableStrategy.py
generic_report_generator_psql/PSQLPersistenceStrategy.py
generic_report_generator_psql/PSQLReportGeneratorFactory.py
generic_report_generator_psql/PSQLResultDownloadStrategy.py
generic_report_generator_psql/__init__.py
generic_report_generator_psql.egg-info/PKG-INFO
generic_report_generator_psql.egg-info/SOURCES.txt
generic_report_generator_psql.egg-info/dependency_links.txt
generic_report_generator_psql.egg-info/requires.txt
generic_report_generator_psql.egg-info/top_level.txt