Metadata-Version: 2.1
Name: generic-report-generator-psql
Version: 0.0.8
Summary: The generic report generator for postgresql
Home-page: https://github.com/davidNHK/generic-report-generator-psql
Author: David Ng
Author-email: david.ng.dev@gmail.com
License: BSD
Platform: UNKNOWN
